{"_path":"/zh_hans/commands/news/showchoices","_dir":"news","_draft":false,"_partial":false,"_locale":"","title":"显示选项","description":"选项是游戏中场景的表现显示，不同的选项执行不同的指令","applicationScope":[199,3,182,193,1,302,325],"body":{"type":"root","children":[{"type":"element","tag":"h2","props":{"id":"选项使用"},"children":[{"type":"text","value":"选项使用"}]},{"type":"element","tag":"blockquote","props":{},"children":[{"type":"element","tag":"p","props":{},"children":[{"type":"text","value":"可以创建多个选项，如RPG中常见的 对话、购买。支持调用字符串变量。"}]}]},{"type":"element","tag":"p","props":{},"children":[{"type":"element","tag":"img","props":{"alt":"alt text","src":"/image/zh_hans/commands/news/showchoices/image.png"},"children":[]}]},{"type":"element","tag":"p","props":{},"children":[{"type":"text","value":"效果"}]},{"type":"element","tag":"p","props":{},"children":[{"type":"element","tag":"img","props":{"alt":"alt text","src":"/image/zh_hans/commands/news/showchoices/image-1.png"},"children":[]}]},{"type":"element","tag":"p","props":{},"children":[{"type":"text","value":"选择 "},{"type":"element","tag":"code","props":{"className":[]},"children":[{"type":"text","value":"我在学习"}]},{"type":"text","value":" 则执行该选项内设定的指令"}]},{"type":"element","tag":"p","props":{},"children":[{"type":"element","tag":"img","props":{"alt":"alt text","src":"/image/zh_hans/commands/news/showchoices/image-2.png"},"children":[]}]},{"type":"element","tag":"h2","props":{"id":"选项设置"},"children":[{"type":"text","value":"选项设置"}]},{"type":"element","tag":"h3","props":{"id":"设为默认选项"},"children":[{"type":"text","value":"设为默认选项"}]},{"type":"element","tag":"p","props":{},"children":[{"type":"text","value":"指定一个选项设置后，显示选项时焦点默认选择设置的选项。"}]},{"type":"element","tag":"p","props":{},"children":[{"type":"element","tag":"img","props":{"alt":"alt text","src":"/image/zh_hans/commands/news/showchoices/image-3.png"},"children":[]}]},{"type":"element","tag":"h3","props":{"id":"设为取消的场合"},"children":[{"type":"text","value":"设为取消的场合"}]},{"type":"element","tag":"p","props":{},"children":[{"type":"text","value":"指定一个选项设置后，当关闭当前选项(如：快捷键ESC)则表示执行此选项"}]},{"type":"element","tag":"p","props":{},"children":[{"type":"element","tag":"img","props":{"alt":"alt text","src":"/image/zh_hans/commands/news/showchoices/image-4.png"},"children":[]}]},{"type":"element","tag":"h3","props":{"id":"设置出现条件"},"children":[{"type":"text","value":"设置出现条件"}]},{"type":"element","tag":"p","props":{},"children":[{"type":"text","value":"类似指令:条件分歧。当满足了设置的条件后，指定的选项出现，否则隐藏"}]},{"type":"element","tag":"p","props":{},"children":[{"type":"element","tag":"img","props":{"alt":"alt text","src":"/image/zh_hans/commands/news/showchoices/image-5.png"},"children":[]}]},{"type":"element","tag":"h2","props":{"id":"对话框样式"},"children":[{"type":"text","value":"对话框样式"}]},{"type":"element","tag":"p","props":{},"children":[{"type":"text","value":"对话最终的样式排版都取决于指定的对话样式。"}]},{"type":"element","tag":"p","props":{},"children":[{"type":"element","tag":"img","props":{"alt":"alt text","src":"/image/zh_hans/commands/news/showchoices/image-6.png"},"children":[]}]},{"type":"element","tag":"h2","props":{"id":"自定义对话框样式"},"children":[{"type":"text","value":"自定义对话框样式"}]},{"type":"element","tag":"p","props":{},"children":[{"type":"text","value":"如果想要自定义对话框样式，可通过 "},{"type":"element","tag":"code","props":{"className":[]},"children":[{"type":"text","value":"数据库(快捷键F10) -> 对话框样式"}]},{"type":"text","value":" 进行增改。"}]},{"type":"element","tag":"p","props":{},"children":[{"type":"text","value":"直接选择对应组件然后替换素材、修改位置即可。步骤全程可视化，所以请大胆尝试。"}]},{"type":"element","tag":"p","props":{},"children":[{"type":"element","tag":"img","props":{"alt":"alt text","src":"/image/zh_hans/commands/news/showchoices/image-7.png"},"children":[]}]}],"toc":{"title":"","searchDepth":2,"depth":2,"links":[{"id":"选项使用","depth":2,"text":"选项使用"},{"id":"选项设置","depth":2,"text":"选项设置","children":[{"id":"设为默认选项","depth":3,"text":"设为默认选项"},{"id":"设为取消的场合","depth":3,"text":"设为取消的场合"},{"id":"设置出现条件","depth":3,"text":"设置出现条件"}]},{"id":"对话框样式","depth":2,"text":"对话框样式"},{"id":"自定义对话框样式","depth":2,"text":"自定义对话框样式"}]}},"_type":"markdown","_id":"content:zh_hans:commands:news:showchoices.md","_source":"content","_file":"zh_hans/commands/news/showchoices.md","_stem":"zh_hans/commands/news/showchoices","_extension":"md"}