{"_path":"/zh_hans/commands/images/showpicture","_dir":"images","_draft":false,"_partial":false,"_locale":"","title":"显示图片","description":"通过该指令可在图像层上显示指定图片","applicationScope":[199,3,182,193,1,302,325],"body":{"type":"root","children":[{"type":"element","tag":"h2","props":{"id":"使用"},"children":[{"type":"text","value":"使用"}]},{"type":"element","tag":"p","props":{},"children":[{"type":"text","value":"通过指定图片即可显示在场景地图上。"}]},{"type":"element","tag":"p","props":{},"children":[{"type":"element","tag":"img","props":{"alt":"alt text","src":"/image/zh_hans/commands/images/showpicture/image.png"},"children":[]}]},{"type":"element","tag":"h2","props":{"id":"开启可视化预览"},"children":[{"type":"text","value":"开启可视化预览"}]},{"type":"element","tag":"p","props":{},"children":[{"type":"text","value":"推荐开启预览事件页模式，能够更加方便的预览游戏效果。"}]},{"type":"element","tag":"p","props":{},"children":[{"type":"text","value":"点击事件页上的这个按钮可以开启事件预览模式，这样就可以可视化预览游戏中的效果。"}]},{"type":"element","tag":"p","props":{},"children":[{"type":"element","tag":"img","props":{"alt":"alt text","src":"/image/zh_hans/commands/images/showpicture/image-1.png"},"children":[]}]},{"type":"element","tag":"p","props":{},"children":[{"type":"element","tag":"img","props":{"alt":"alt text","src":"/image/zh_hans/commands/images/showpicture/image-2.png"},"children":[]}]},{"type":"element","tag":"h2","props":{"id":"编号"},"children":[{"type":"text","value":"编号"}]},{"type":"element","tag":"p","props":{},"children":[{"type":"text","value":"图像类型的指令都拥有编号，编号的作用类似变量编号一样。"}]},{"type":"element","tag":"p","props":{},"children":[{"type":"text","value":"编号也涉及到了图像之间的层级关系。"}]},{"type":"element","tag":"p","props":{},"children":[{"type":"text","value":"如下图中，显示动画编号是1，显示图片编号是2。所以显示图片层级比显示动画高。"}]},{"type":"element","tag":"p","props":{},"children":[{"type":"element","tag":"img","props":{"alt":"alt text","src":"/image/zh_hans/commands/images/showpicture/image-3.png"},"children":[]}]},{"type":"element","tag":"h2","props":{"id":"高级设定"},"children":[{"type":"text","value":"高级设定"}]},{"type":"element","tag":"p","props":{},"children":[{"type":"text","value":"开启高级设定，可以将指定源变为指定变量。"}]},{"type":"element","tag":"p","props":{},"children":[{"type":"element","tag":"img","props":{"alt":"alt text","src":"/image/zh_hans/commands/images/showpicture/image-4.png"},"children":[]}]}],"toc":{"title":"","searchDepth":2,"depth":2,"links":[{"id":"使用","depth":2,"text":"使用"},{"id":"开启可视化预览","depth":2,"text":"开启可视化预览"},{"id":"编号","depth":2,"text":"编号"},{"id":"高级设定","depth":2,"text":"高级设定"}]}},"_type":"markdown","_id":"content:zh_hans:commands:images:showpicture.md","_source":"content","_file":"zh_hans/commands/images/showpicture.md","_stem":"zh_hans/commands/images/showpicture","_extension":"md"}